mongo_client/__init__.py
mongo_client/client.py
mongo_client/py.typed
actvalue_mongo_client-0.1.0.dist-info/METADATA
actvalue_mongo_client-0.1.0.dist-info/WHEEL
actvalue_mongo_client-0.1.0.dist-info/RECORD
