Metadata-Version: 2.4
Name: actvalue.mongo-client
Version: 0.1.0
Summary: Singleton MongoDB client for AWS Lambda and serverless environments
Project-URL: Homepage, https://github.com/pmosconi/mongo-client
Project-URL: Repository, https://github.com/pmosconi/mongo-client
Author: ActValue
License: MIT
Keywords: async,connection-pool,lambda,mongodb,serverless,singleton
Classifier: Development Status :: 5 - Production/Stable
Classifier: Framework :: AsyncIO
Classifier: Intended Audience :: Developers
Classifier: License :: OSI Approved :: MIT License
Classifier: Programming Language :: Python :: 3
Classifier: Programming Language :: Python :: 3.13
Classifier: Topic :: Database
Classifier: Topic :: Software Development :: Libraries :: Python Modules
Requires-Python: >=3.13
Requires-Dist: pymongo>=4.15.0
Provides-Extra: dev
Requires-Dist: mypy>=1.8.0; extra == 'dev'
Requires-Dist: pytest-asyncio>=0.23.0; extra == 'dev'
Requires-Dist: pytest-cov>=4.1.0; extra == 'dev'
Requires-Dist: pytest>=8.0.0; extra == 'dev'
Requires-Dist: ruff>=0.7.0; extra == 'dev'
